flake8_pep604.py
flake8_pep604-1.1.0.dist-info/LICENSE
flake8_pep604-1.1.0.dist-info/METADATA
flake8_pep604-1.1.0.dist-info/WHEEL
flake8_pep604-1.1.0.dist-info/entry_points.txt
flake8_pep604-1.1.0.dist-info/top_level.txt
flake8_pep604-1.1.0.dist-info/RECORD
