Metadata-Version: 2.1
Name: flake8-pep604
Version: 1.1.0
Summary: flake8 plugin to enforce use of `|` over `typing.Union`
Home-page: https://gitlab.com/matthewhughes/flake-pep604
Author: Matthew Hughes
Author-email: matthewhughes934@gmail.com
License: MIT
Platform: UNKNOWN
Classifier: License :: OSI Approved :: MIT License
Classifier: Programming Language :: Python :: 3
Classifier: Programming Language :: Python :: 3 :: Only
Classifier: Programming Language :: Python :: 3.7
Classifier: Programming Language :: Python :: 3.8
Classifier: Programming Language :: Python :: 3.9
Classifier: Programming Language :: Python :: 3.10
Classifier: Programming Language :: Python :: Implementation :: CPython
Requires-Python: >=3.7
License-File: LICENSE
Requires-Dist: flake8 (>=3.8)
Requires-Dist: importlib-metadata ; python_version < "3.8"
